{"allocation_method":null,"api_path":"/api/v1/2024/zips/02199.json","api_version":"v1","assigned_incident_count":767,"comparison_scope":"source_universe","comparison_scope_value":"","confidence_grade":"A","county_components":null,"county_count":0,"county_fips":null,"county_name":null,"coverage_status":"observed","data_coverage_score":0.991,"data_source_type":"observed","drug_crime_count":1,"drug_percentile":0.618599175985874,"drug_rate_per_1000":0.7739938080495357,"drug_score_0_100":61.9,"drug_score_label":"high","is_modeled":false,"observed_level":"zcta","other_crime_count":183,"other_percentile":0.9952913478516775,"other_rate_per_1000":141.64086687306502,"other_score_0_100":99.5,"other_score_label":"very_high","overall_crime_score_0_100":83.1,"overall_crime_score_label":"very_high","overall_percentile":0.886992348440259,"population_total":1292,"property_crime_count":463,"property_percentile":0.9888169511477339,"property_rate_per_1000":358.359133126935,"property_score_0_100":98.9,"property_score_label":"very_high","public_order_crime_count":52,"public_order_percentile":0.9434961742201294,"public_order_rate_per_1000":40.247678018575854,"public_order_score_0_100":94.3,"public_order_score_label":"very_high","score_notes":null,"source_count":1,"source_names":"boston_2024","spatial_incident_count":767,"total_crime_count":767,"total_crime_percentile":0.987051206592113,"total_crime_score_0_100":98.7,"total_crime_score_label":"very_high","total_rate_per_1000":593.6532507739938,"unknown_crime_count":0,"violent_crime_count":68,"violent_percentile":0.9493819894055326,"violent_rate_per_1000":52.63157894736842,"violent_score_0_100":94.9,"violent_score_label":"very_high","weapons_crime_count":0,"weapons_percentile":0.17951736315479694,"weapons_rate_per_1000":0.0,"weapons_score_0_100":18.0,"weapons_score_label":"very_low","year":2024,"zcta":"02199","zip":"02199"}