{"api_path":"/api/v1/2024/zips/10069.json","api_version":"v1","assigned_incident_count":94,"comparison_scope":"national_combined","comparison_scope_value":"","confidence_grade":"A","coverage_status":"observed","data_coverage_score":0.993,"data_source_type":"observed","drug_crime_count":0,"drug_percentile":0.22707034728406056,"drug_rate_per_1000":0.0,"drug_score_0_100":22.7,"drug_score_label":"low","is_modeled":false,"other_crime_count":0,"other_percentile":0.28227960819234194,"other_rate_per_1000":0.0,"other_score_0_100":28.2,"other_score_label":"low","overall_crime_score_0_100":30.7,"overall_crime_score_label":"low","overall_percentile":0.2920747996438112,"population_total":6509,"property_crime_count":50,"property_percentile":0.3054318788958148,"property_rate_per_1000":7.6816715317253035,"property_score_0_100":30.5,"property_score_label":"low","public_order_crime_count":26,"public_order_percentile":0.44434550311665183,"public_order_rate_per_1000":3.9944691964971577,"public_order_score_0_100":44.4,"public_order_score_label":"average","score_notes":null,"source_count":1,"source_names":"nyc_2024","spatial_incident_count":94,"total_crime_count":94,"total_crime_percentile":0.3072128227960819,"total_crime_score_0_100":30.7,"total_crime_score_label":"low","total_rate_per_1000":14.44154247964357,"unknown_crime_count":0,"violent_crime_count":18,"violent_percentile":0.3499554764024933,"violent_rate_per_1000":2.765401751421109,"violent_score_0_100":35.0,"violent_score_label":"low","weapons_crime_count":0,"weapons_percentile":0.18655387355298308,"weapons_rate_per_1000":0.0,"weapons_score_0_100":18.7,"weapons_score_label":"very_low","year":2024,"zcta":"10069","zip":"10069"}