{"allocation_method":"zip_county_rate_allocation","api_path":"/api/v1/2024/zips/27829.json","api_version":"v1","assigned_incident_count":0,"comparison_scope":"national_combined","comparison_scope_value":"","confidence_grade":"C","county_components":"[{\"county_fips\":\"37065\",\"county_name\":\"Edgecombe County\",\"weight\":0.205654},{\"county_fips\":\"37147\",\"county_name\":\"Pitt County\",\"weight\":0.63438},{\"county_fips\":\"37195\",\"county_name\":\"Wilson County\",\"weight\":0.159966}]","county_count":3,"county_fips":"37065|37147|37195","county_name":"Edgecombe County|Pitt County|Wilson County","coverage_status":"county_observed_allocated","data_coverage_score":0.75,"data_source_type":"observed","drug_crime_count":null,"drug_percentile":null,"drug_rate_per_1000":null,"drug_score_0_100":null,"drug_score_label":"unavailable","is_modeled":false,"observed_level":"county","other_crime_count":null,"other_percentile":null,"other_rate_per_1000":null,"other_score_0_100":null,"other_score_label":"unavailable","overall_crime_score_0_100":80.1,"overall_crime_score_label":"very_high","overall_percentile":0.8176825396825397,"population_total":1664,"property_crime_count":31,"property_percentile":0.823047619047619,"property_rate_per_1000":18.629807692307693,"property_score_0_100":82.3,"property_score_label":"very_high","public_order_crime_count":null,"public_order_percentile":null,"public_order_rate_per_1000":null,"public_order_score_0_100":null,"public_order_score_label":"unavailable","score_notes":"renormalized_missing_categories:drug,public_order,weapons,other; county_observed_allocated_from_fbi_cde_cius; ZIP values are estimated from county-level rates","source_count":3,"source_names":"fbi_cde_cius_offenses_known","spatial_incident_count":0,"total_crime_count":37,"total_crime_percentile":0.814031746031746,"total_crime_score_0_100":81.4,"total_crime_score_label":"very_high","total_rate_per_1000":22.235576923076923,"unknown_crime_count":null,"violent_crime_count":6,"violent_percentile":0.7838095238095238,"violent_rate_per_1000":3.605769230769231,"violent_score_0_100":78.4,"violent_score_label":"high","weapons_crime_count":null,"weapons_percentile":null,"weapons_rate_per_1000":null,"weapons_score_0_100":null,"weapons_score_label":"unavailable","year":2024,"zcta":"27829","zip":"27829"}