{"allocation_method":"zip_county_rate_allocation","api_path":"/api/v1/2024/zips/30004.json","api_version":"v1","assigned_incident_count":0,"comparison_scope":"national_combined","comparison_scope_value":"","confidence_grade":"C","county_components":"[{\"county_fips\":\"13057\",\"county_name\":\"Cherokee County\",\"weight\":0.156285},{\"county_fips\":\"13117\",\"county_name\":\"Forsyth County\",\"weight\":0.160339},{\"county_fips\":\"13121\",\"county_name\":\"Fulton County\",\"weight\":0.683376}]","county_count":3,"county_fips":"13057|13117|13121","county_name":"Cherokee County|Forsyth County|Fulton County","coverage_status":"county_observed_allocated","data_coverage_score":0.75,"data_source_type":"observed","drug_crime_count":null,"drug_percentile":null,"drug_rate_per_1000":null,"drug_score_0_100":null,"drug_score_label":"unavailable","is_modeled":false,"observed_level":"county","other_crime_count":null,"other_percentile":null,"other_rate_per_1000":null,"other_score_0_100":null,"other_score_label":"unavailable","overall_crime_score_0_100":45.7,"overall_crime_score_label":"average","overall_percentile":0.46684126984126983,"population_total":68707,"property_crime_count":575,"property_percentile":0.47025396825396826,"property_rate_per_1000":8.36887071186342,"property_score_0_100":47.0,"property_score_label":"average","public_order_crime_count":null,"public_order_percentile":null,"public_order_rate_per_1000":null,"public_order_score_0_100":null,"public_order_score_label":"unavailable","score_notes":"renormalized_missing_categories:drug,public_order,weapons,other; county_observed_allocated_from_fbi_cde_cius; ZIP values are estimated from county-level rates","source_count":3,"source_names":"fbi_cde_cius_offenses_known","spatial_incident_count":0,"total_crime_count":674,"total_crime_percentile":0.4510793650793651,"total_crime_score_0_100":45.1,"total_crime_score_label":"average","total_rate_per_1000":9.809771930079904,"unknown_crime_count":null,"violent_crime_count":100,"violent_percentile":0.4481904761904762,"violent_rate_per_1000":1.455455775976247,"violent_score_0_100":44.8,"violent_score_label":"average","weapons_crime_count":null,"weapons_percentile":null,"weapons_rate_per_1000":null,"weapons_score_0_100":null,"weapons_score_label":"unavailable","year":2024,"zcta":"30004","zip":"30004"}