{"allocation_method":"zip_county_rate_allocation","api_path":"/api/v1/2024/zips/46573.json","api_version":"v1","assigned_incident_count":0,"comparison_scope":"national_combined","comparison_scope_value":"","confidence_grade":"C","county_components":"[{\"county_fips\":\"18039\",\"county_name\":\"Elkhart County\",\"weight\":0.509827},{\"county_fips\":\"18141\",\"county_name\":\"St. Joseph County\",\"weight\":0.490173}]","county_count":2,"county_fips":"18039|18141","county_name":"Elkhart County|St. Joseph County","coverage_status":"county_observed_allocated","data_coverage_score":0.75,"data_source_type":"observed","drug_crime_count":null,"drug_percentile":null,"drug_rate_per_1000":null,"drug_score_0_100":null,"drug_score_label":"unavailable","is_modeled":false,"observed_level":"county","other_crime_count":null,"other_percentile":null,"other_rate_per_1000":null,"other_score_0_100":null,"other_score_label":"unavailable","overall_crime_score_0_100":83.0,"overall_crime_score_label":"very_high","overall_percentile":0.8489894495995932,"population_total":3936,"property_crime_count":60,"property_percentile":0.7845748061522817,"property_rate_per_1000":15.24390243902439,"property_score_0_100":78.5,"property_score_label":"high","public_order_crime_count":null,"public_order_percentile":null,"public_order_rate_per_1000":null,"public_order_score_0_100":null,"public_order_score_label":"unavailable","score_notes":"renormalized_missing_categories:drug,public_order,weapons,other; county_observed_allocated_from_fbi_cde_cius; ZIP values are estimated from county-level rates","source_count":2,"source_names":"fbi_cde_cius_offenses_known","spatial_incident_count":0,"total_crime_count":76,"total_crime_percentile":0.7966505656539977,"total_crime_score_0_100":79.7,"total_crime_score_label":"high","total_rate_per_1000":19.308943089430894,"unknown_crime_count":null,"violent_crime_count":16,"violent_percentile":0.8627335706114148,"violent_rate_per_1000":4.065040650406504,"violent_score_0_100":86.3,"violent_score_label":"very_high","weapons_crime_count":null,"weapons_percentile":null,"weapons_rate_per_1000":null,"weapons_score_0_100":null,"weapons_score_label":"unavailable","year":2024,"zcta":"46573","zip":"46573"}