{"allocation_method":null,"api_path":"/api/v1/2024/zips/48205.json","api_version":"v1","assigned_incident_count":5292,"comparison_scope":"source_universe","comparison_scope_value":"","confidence_grade":"A","county_components":null,"county_count":0,"county_fips":null,"county_name":null,"coverage_status":"observed","data_coverage_score":0.991,"data_source_type":"observed","drug_crime_count":1,"drug_percentile":0.3360800470865215,"drug_rate_per_1000":0.029250884839266387,"drug_score_0_100":33.6,"drug_score_label":"low","is_modeled":false,"observed_level":"zcta","other_crime_count":95,"other_percentile":0.857563272513243,"other_rate_per_1000":2.7788340597303067,"other_score_0_100":85.8,"other_score_label":"very_high","overall_crime_score_0_100":87.8,"overall_crime_score_label":"very_high","overall_percentile":0.9437904649793997,"population_total":34187,"property_crime_count":2651,"property_percentile":0.901706886403767,"property_rate_per_1000":77.5440957088952,"property_score_0_100":90.2,"property_score_label":"very_high","public_order_crime_count":28,"public_order_percentile":0.4155385520894644,"public_order_rate_per_1000":0.8190247754994588,"public_order_score_0_100":41.6,"public_order_score_label":"average","score_notes":null,"source_count":1,"source_names":"detroit_2024","spatial_incident_count":5292,"total_crime_count":5292,"total_crime_percentile":0.8958210712183637,"total_crime_score_0_100":89.6,"total_crime_score_label":"very_high","total_rate_per_1000":154.7956825693977,"unknown_crime_count":414,"violent_crime_count":1846,"violent_percentile":0.951736315479694,"violent_rate_per_1000":53.99713341328575,"violent_score_0_100":95.2,"violent_score_label":"very_high","weapons_crime_count":257,"weapons_percentile":0.9752795762213067,"weapons_rate_per_1000":7.517477403691462,"weapons_score_0_100":97.5,"weapons_score_label":"very_high","year":2024,"zcta":"48205","zip":"48205"}