{"allocation_method":null,"api_path":"/api/v1/2024/zips/80220.json","api_version":"v1","assigned_incident_count":3500,"comparison_scope":"source_universe","comparison_scope_value":"","confidence_grade":"A","county_components":null,"county_count":0,"county_fips":null,"county_name":null,"coverage_status":"observed","data_coverage_score":0.991,"data_source_type":"observed","drug_crime_count":292,"drug_percentile":0.9175985874043555,"drug_rate_per_1000":7.84882939547886,"drug_score_0_100":91.8,"drug_score_label":"very_high","is_modeled":false,"observed_level":"zcta","other_crime_count":685,"other_percentile":0.9446733372572101,"other_rate_per_1000":18.41249361610623,"other_score_0_100":94.5,"other_score_label":"very_high","overall_crime_score_0_100":63.6,"overall_crime_score_label":"high","overall_percentile":0.6509711595055915,"population_total":37203,"property_crime_count":1609,"property_percentile":0.7451442024720424,"property_rate_per_1000":43.249200333306455,"property_score_0_100":74.5,"property_score_label":"high","public_order_crime_count":531,"public_order_percentile":0.7598587404355504,"public_order_rate_per_1000":14.273042496572858,"public_order_score_0_100":76.0,"public_order_score_label":"high","score_notes":null,"source_count":2,"source_names":"colorado_springs_2024|denver_2024","spatial_incident_count":3500,"total_crime_count":3500,"total_crime_percentile":0.7816362566215421,"total_crime_score_0_100":78.2,"total_crime_score_label":"high","total_rate_per_1000":94.07843453484934,"unknown_crime_count":0,"violent_crime_count":383,"violent_percentile":0.6356680400235433,"violent_rate_per_1000":10.294868693384942,"violent_score_0_100":63.6,"violent_score_label":"high","weapons_crime_count":0,"weapons_percentile":0.17951736315479694,"weapons_rate_per_1000":0.0,"weapons_score_0_100":18.0,"weapons_score_label":"very_low","year":2024,"zcta":"80220","zip":"80220"}