{"allocation_method":"zip_county_rate_allocation","api_path":"/api/v1/2024/zips/95004.json","api_version":"v1","assigned_incident_count":0,"comparison_scope":"national_combined","comparison_scope_value":"","confidence_grade":"C","county_components":"[{\"county_fips\":\"06053\",\"county_name\":\"Monterey County\",\"weight\":0.5637},{\"county_fips\":\"06069\",\"county_name\":\"San Benito County\",\"weight\":0.4363}]","county_count":2,"county_fips":"06053|06069","county_name":"Monterey County|San Benito County","coverage_status":"county_observed_allocated","data_coverage_score":0.75,"data_source_type":"observed","drug_crime_count":null,"drug_percentile":null,"drug_rate_per_1000":null,"drug_score_0_100":null,"drug_score_label":"unavailable","is_modeled":false,"observed_level":"county","other_crime_count":null,"other_percentile":null,"other_rate_per_1000":null,"other_score_0_100":null,"other_score_label":"unavailable","overall_crime_score_0_100":78.4,"overall_crime_score_label":"high","overall_percentile":0.8014173128257277,"population_total":4363,"property_crime_count":50,"property_percentile":0.6621806279394941,"property_rate_per_1000":11.460004584001833,"property_score_0_100":66.2,"property_score_label":"high","public_order_crime_count":null,"public_order_percentile":null,"public_order_rate_per_1000":null,"public_order_score_0_100":null,"public_order_score_label":"unavailable","score_notes":"renormalized_missing_categories:drug,public_order,weapons,other; county_observed_allocated_from_fbi_cde_cius; ZIP values are estimated from county-level rates","source_count":2,"source_names":"fbi_cde_cius_offenses_known","spatial_incident_count":0,"total_crime_count":68,"total_crime_percentile":0.7190479216982332,"total_crime_score_0_100":71.9,"total_crime_score_label":"high","total_rate_per_1000":15.585606234242494,"unknown_crime_count":null,"violent_crime_count":19,"violent_percentile":0.8758421253336723,"violent_rate_per_1000":4.354801741920697,"violent_score_0_100":87.6,"violent_score_label":"very_high","weapons_crime_count":null,"weapons_percentile":null,"weapons_rate_per_1000":null,"weapons_score_0_100":null,"weapons_score_label":"unavailable","year":2024,"zcta":"95004","zip":"95004"}