{"allocation_method":null,"api_path":"/api/v1/2024/zips/02131.json","api_version":"v1","assigned_incident_count":1593,"comparison_scope":"source_universe","comparison_scope_value":"","confidence_grade":"A","county_components":null,"county_count":0,"county_fips":null,"county_name":null,"coverage_status":"observed","data_coverage_score":0.993,"data_source_type":"observed","drug_crime_count":8,"drug_percentile":0.5603663613655288,"drug_rate_per_1000":0.2568135854386697,"drug_score_0_100":56.0,"drug_score_label":"average","is_modeled":false,"observed_level":"zcta","other_crime_count":675,"other_percentile":0.9375520399666945,"other_rate_per_1000":21.668646271387757,"other_score_0_100":93.8,"other_score_label":"very_high","overall_crime_score_0_100":45.7,"overall_crime_score_label":"average","overall_percentile":0.4196502914238135,"population_total":31151,"property_crime_count":358,"property_percentile":0.3288925895087427,"property_rate_per_1000":11.49240794838047,"property_score_0_100":32.9,"property_score_label":"low","public_order_crime_count":405,"public_order_percentile":0.6569525395503747,"public_order_rate_per_1000":13.001187762832654,"public_order_score_0_100":65.7,"public_order_score_label":"high","score_notes":null,"source_count":1,"source_names":"boston_2024","spatial_incident_count":1593,"total_crime_count":1593,"total_crime_percentile":0.5378850957535387,"total_crime_score_0_100":53.8,"total_crime_score_label":"average","total_rate_per_1000":51.1380052004751,"unknown_crime_count":0,"violent_crime_count":136,"violent_percentile":0.4113238967527061,"violent_rate_per_1000":4.365830952457385,"violent_score_0_100":41.1,"violent_score_label":"average","weapons_crime_count":11,"weapons_percentile":0.5728559533721899,"weapons_rate_per_1000":0.35311867997817087,"weapons_score_0_100":57.3,"weapons_score_label":"average","year":2024,"zcta":"02131","zip":"02131"}