{"allocation_method":null,"api_path":"/api/v1/2024/zips/10033.json","api_version":"v1","assigned_incident_count":3779,"comparison_scope":"source_universe","comparison_scope_value":"","confidence_grade":"A","county_components":null,"county_count":0,"county_fips":null,"county_name":null,"coverage_status":"observed","data_coverage_score":0.991,"data_source_type":"observed","drug_crime_count":152,"drug_percentile":0.7904649793996469,"drug_rate_per_1000":2.7718005762427516,"drug_score_0_100":79.0,"drug_score_label":"high","is_modeled":false,"observed_level":"zcta","other_crime_count":0,"other_percentile":0.25338434373160684,"other_rate_per_1000":0.0,"other_score_0_100":25.3,"other_score_label":"low","overall_crime_score_0_100":68.3,"overall_crime_score_label":"high","overall_percentile":0.7151265450264862,"population_total":54838,"property_crime_count":1691,"property_percentile":0.6456739258387286,"property_rate_per_1000":30.836281410700607,"property_score_0_100":64.6,"property_score_label":"high","public_order_crime_count":1123,"public_order_percentile":0.8346085932901707,"public_order_rate_per_1000":20.478500310004012,"public_order_score_0_100":83.5,"public_order_score_label":"very_high","score_notes":null,"source_count":1,"source_names":"nyc_2024","spatial_incident_count":3779,"total_crime_count":3779,"total_crime_percentile":0.6768687463213655,"total_crime_score_0_100":67.7,"total_crime_score_label":"high","total_rate_per_1000":68.91206827382472,"unknown_crime_count":3,"violent_crime_count":749,"violent_percentile":0.7033549146556798,"violent_rate_per_1000":13.658412050038296,"violent_score_0_100":70.3,"violent_score_label":"high","weapons_crime_count":61,"weapons_percentile":0.7633902295467923,"weapons_rate_per_1000":1.1123673365184725,"weapons_score_0_100":76.3,"weapons_score_label":"high","year":2024,"zcta":"10033","zip":"10033"}