{"allocation_method":null,"api_path":"/api/v1/2024/zips/11232.json","api_version":"v1","assigned_incident_count":1983,"comparison_scope":"national_combined","comparison_scope_value":"","confidence_grade":"A","county_components":null,"county_count":0,"county_fips":null,"county_name":null,"coverage_status":"observed","data_coverage_score":0.993,"data_source_type":"observed","drug_crime_count":35,"drug_percentile":0.7399821905609973,"drug_rate_per_1000":1.2582686223756112,"drug_score_0_100":74.0,"drug_score_label":"high","is_modeled":false,"observed_level":"zcta","other_crime_count":0,"other_percentile":0.28227960819234194,"other_rate_per_1000":0.0,"other_score_0_100":28.2,"other_score_label":"low","overall_crime_score_0_100":67.7,"overall_crime_score_label":"high","overall_percentile":0.7146037399821905,"population_total":27816,"property_crime_count":706,"property_percentile":0.560106856634016,"property_rate_per_1000":25.38107563991947,"property_score_0_100":56.0,"property_score_label":"average","public_order_crime_count":684,"public_order_percentile":0.8210151380231523,"public_order_rate_per_1000":24.59016393442623,"public_order_score_0_100":82.1,"public_order_score_label":"very_high","score_notes":null,"source_count":1,"source_names":"nyc_2024","spatial_incident_count":1983,"total_crime_count":1983,"total_crime_percentile":0.6562778272484416,"total_crime_score_0_100":65.6,"total_crime_score_label":"high","total_rate_per_1000":71.28990509059534,"unknown_crime_count":0,"violent_crime_count":537,"violent_percentile":0.773820124666073,"violent_rate_per_1000":19.305435720448664,"violent_score_0_100":77.4,"violent_score_label":"high","weapons_crime_count":21,"weapons_percentile":0.7150489759572574,"weapons_rate_per_1000":0.7549611734253667,"weapons_score_0_100":71.5,"weapons_score_label":"high","year":2024,"zcta":"11232","zip":"11232"}