{"allocation_method":null,"api_path":"/api/v1/2024/zips/11429.json","api_version":"v1","assigned_incident_count":1211,"comparison_scope":"source_universe","comparison_scope_value":"","confidence_grade":"A","county_components":null,"county_count":0,"county_fips":null,"county_name":null,"coverage_status":"observed","data_coverage_score":0.993,"data_source_type":"observed","drug_crime_count":13,"drug_percentile":0.6319733555370525,"drug_rate_per_1000":0.4844961240310077,"drug_score_0_100":63.2,"drug_score_label":"high","is_modeled":false,"observed_level":"zcta","other_crime_count":0,"other_percentile":0.2785179017485429,"other_rate_per_1000":0.0,"other_score_0_100":27.9,"other_score_label":"low","overall_crime_score_0_100":52.5,"overall_crime_score_label":"average","overall_percentile":0.5108243130724396,"population_total":26832,"property_crime_count":319,"property_percentile":0.33638634471273937,"property_rate_per_1000":11.888789505068575,"property_score_0_100":33.6,"property_score_label":"low","public_order_crime_count":606,"public_order_percentile":0.8076602830974188,"public_order_rate_per_1000":22.584973166368513,"public_order_score_0_100":80.8,"public_order_score_label":"very_high","score_notes":null,"source_count":1,"source_names":"nyc_2024","spatial_incident_count":1211,"total_crime_count":1211,"total_crime_percentile":0.5029142381348876,"total_crime_score_0_100":50.3,"total_crime_score_label":"average","total_rate_per_1000":45.13267740011926,"unknown_crime_count":0,"violent_crime_count":255,"violent_percentile":0.5920066611157369,"violent_rate_per_1000":9.503577817531305,"violent_score_0_100":59.2,"violent_score_label":"average","weapons_crime_count":18,"weapons_percentile":0.678601165695254,"weapons_rate_per_1000":0.6708407871198568,"weapons_score_0_100":67.9,"weapons_score_label":"high","year":2024,"zcta":"11429","zip":"11429"}