{"allocation_method":null,"api_path":"/api/v1/2024/zips/19148.json","api_version":"v1","assigned_incident_count":4156,"comparison_scope":"source_universe","comparison_scope_value":"","confidence_grade":"A","county_components":null,"county_count":0,"county_fips":null,"county_name":null,"coverage_status":"observed","data_coverage_score":0.991,"data_source_type":"observed","drug_crime_count":14,"drug_percentile":0.503825779870512,"drug_rate_per_1000":0.2777777777777778,"drug_score_0_100":50.4,"drug_score_label":"average","is_modeled":false,"observed_level":"zcta","other_crime_count":0,"other_percentile":0.25338434373160684,"other_rate_per_1000":0.0,"other_score_0_100":25.3,"other_score_label":"low","overall_crime_score_0_100":71.9,"overall_crime_score_label":"high","overall_percentile":0.7583872866391995,"population_total":50400,"property_crime_count":2540,"property_percentile":0.786933490288405,"property_rate_per_1000":50.3968253968254,"property_score_0_100":78.7,"property_score_label":"high","public_order_crime_count":601,"public_order_percentile":0.723955267804591,"public_order_rate_per_1000":11.924603174603174,"public_order_score_0_100":72.4,"public_order_score_label":"high","score_notes":null,"source_count":1,"source_names":"philadelphia_2024","spatial_incident_count":4156,"total_crime_count":4156,"total_crime_percentile":0.736904061212478,"total_crime_score_0_100":73.7,"total_crime_score_label":"high","total_rate_per_1000":82.46031746031746,"unknown_crime_count":0,"violent_crime_count":979,"violent_percentile":0.7904649793996469,"violent_rate_per_1000":19.424603174603174,"violent_score_0_100":79.0,"violent_score_label":"high","weapons_crime_count":22,"weapons_percentile":0.618599175985874,"weapons_rate_per_1000":0.4365079365079365,"weapons_score_0_100":61.9,"weapons_score_label":"high","year":2024,"zcta":"19148","zip":"19148"}