{"allocation_method":null,"api_path":"/api/v1/2024/zips/32208.json","api_version":"v1","assigned_incident_count":3915,"comparison_scope":"source_universe","comparison_scope_value":"","confidence_grade":"A","county_components":null,"county_count":0,"county_fips":null,"county_name":null,"coverage_status":"observed","data_coverage_score":0.99,"data_source_type":"observed","drug_crime_count":301,"drug_percentile":0.9346674514420247,"drug_rate_per_1000":9.205174470167284,"drug_score_0_100":93.5,"drug_score_label":"very_high","is_modeled":false,"observed_level":"zcta","other_crime_count":357,"other_percentile":0.9264273101824603,"other_rate_per_1000":10.917765069268174,"other_score_0_100":92.6,"other_score_label":"very_high","overall_crime_score_0_100":85.1,"overall_crime_score_label":"very_high","overall_percentile":0.90759270158917,"population_total":32699,"property_crime_count":1351,"property_percentile":0.7263095938787522,"property_rate_per_1000":41.316248203308966,"property_score_0_100":72.6,"property_score_label":"high","public_order_crime_count":609,"public_order_percentile":0.8187168922895821,"public_order_rate_per_1000":18.624422765222178,"public_order_score_0_100":81.9,"public_order_score_label":"very_high","score_notes":null,"source_count":1,"source_names":"jacksonville_jso_2024","spatial_incident_count":3889,"total_crime_count":3915,"total_crime_percentile":0.8452030606238964,"total_crime_score_0_100":84.5,"total_crime_score_label":"very_high","total_rate_per_1000":119.72843206214257,"unknown_crime_count":0,"violent_crime_count":1167,"violent_percentile":0.899941141848146,"violent_rate_per_1000":35.68916480626319,"violent_score_0_100":90.0,"violent_score_label":"very_high","weapons_crime_count":130,"weapons_percentile":0.9311359623307828,"weapons_rate_per_1000":3.9756567479127805,"weapons_score_0_100":93.1,"weapons_score_label":"very_high","year":2024,"zcta":"32208","zip":"32208"}