{"allocation_method":null,"api_path":"/api/v1/2024/zips/60803.json","api_version":"v1","assigned_incident_count":47,"comparison_scope":"source_universe","comparison_scope_value":"","confidence_grade":"A","county_components":null,"county_count":0,"county_fips":null,"county_name":null,"coverage_status":"observed","data_coverage_score":0.993,"data_source_type":"observed","drug_crime_count":0,"drug_percentile":0.22707034728406056,"drug_rate_per_1000":0.0,"drug_score_0_100":22.7,"drug_score_label":"low","is_modeled":false,"observed_level":"zcta","other_crime_count":0,"other_percentile":0.28227960819234194,"other_rate_per_1000":0.0,"other_score_0_100":28.2,"other_score_label":"low","overall_crime_score_0_100":24.7,"overall_crime_score_label":"low","overall_percentile":0.2439893143365984,"population_total":22106,"property_crime_count":15,"property_percentile":0.22617987533392697,"property_rate_per_1000":0.6785488102777526,"property_score_0_100":22.6,"property_score_label":"low","public_order_crime_count":15,"public_order_percentile":0.3187889581478183,"public_order_rate_per_1000":0.6785488102777526,"public_order_score_0_100":31.9,"public_order_score_label":"low","score_notes":null,"source_count":1,"source_names":"chicago_2024","spatial_incident_count":47,"total_crime_count":47,"total_crime_percentile":0.2341941228851291,"total_crime_score_0_100":23.4,"total_crime_score_label":"low","total_rate_per_1000":2.1261196055369584,"unknown_crime_count":0,"violent_crime_count":17,"violent_percentile":0.2742653606411398,"violent_rate_per_1000":0.769021984981453,"violent_score_0_100":27.4,"violent_score_label":"low","weapons_crime_count":0,"weapons_percentile":0.18655387355298308,"weapons_rate_per_1000":0.0,"weapons_score_0_100":18.7,"weapons_score_label":"very_low","year":2024,"zcta":"60803","zip":"60803"}