{"allocation_method":null,"api_path":"/api/v1/2024/zips/85013.json","api_version":"v1","assigned_incident_count":1204,"comparison_scope":"source_universe","comparison_scope_value":"","confidence_grade":"C","county_components":null,"county_count":0,"county_fips":null,"county_name":null,"coverage_status":"observed","data_coverage_score":0.741,"data_source_type":"observed","drug_crime_count":76,"drug_percentile":0.8198940553266627,"drug_rate_per_1000":3.3792796798577145,"drug_score_0_100":82.0,"drug_score_label":"very_high","is_modeled":false,"observed_level":"zcta","other_crime_count":0,"other_percentile":0.25338434373160684,"other_rate_per_1000":0.0,"other_score_0_100":25.3,"other_score_label":"low","overall_crime_score_0_100":55.4,"overall_crime_score_label":"average","overall_percentile":0.5412007062978222,"population_total":22490,"property_crime_count":900,"property_percentile":0.7168922895821072,"property_rate_per_1000":40.01778568252556,"property_score_0_100":71.7,"property_score_label":"high","public_order_crime_count":0,"public_order_percentile":0.1038846380223661,"public_order_rate_per_1000":0.0,"public_order_score_0_100":10.4,"public_order_score_label":"very_low","score_notes":null,"source_count":1,"source_names":"phoenix_pd_2024","spatial_incident_count":0,"total_crime_count":1204,"total_crime_percentile":0.5991759858740435,"total_crime_score_0_100":59.9,"total_crime_score_label":"average","total_rate_per_1000":53.534904401956425,"unknown_crime_count":0,"violent_crime_count":228,"violent_percentile":0.6321365509123014,"violent_rate_per_1000":10.137839039573144,"violent_score_0_100":63.2,"violent_score_label":"high","weapons_crime_count":0,"weapons_percentile":0.17951736315479694,"weapons_rate_per_1000":0.0,"weapons_score_0_100":18.0,"weapons_score_label":"very_low","year":2024,"zcta":"85013","zip":"85013"}