{"allocation_method":null,"api_path":"/api/v1/2024/zips/90260.json","api_version":"v1","assigned_incident_count":1564,"comparison_scope":"source_universe","comparison_scope_value":"","confidence_grade":"A","county_components":null,"county_count":0,"county_fips":null,"county_name":null,"coverage_status":"observed","data_coverage_score":0.983,"data_source_type":"observed","drug_crime_count":277,"drug_percentile":0.9293702177751618,"drug_rate_per_1000":8.636009353078723,"drug_score_0_100":92.9,"drug_score_label":"very_high","is_modeled":false,"observed_level":"zcta","other_crime_count":175,"other_percentile":0.8934667451442024,"other_rate_per_1000":5.455962587685113,"other_score_0_100":89.3,"other_score_label":"very_high","overall_crime_score_0_100":59.2,"overall_crime_score_label":"average","overall_percentile":0.5927015891701001,"population_total":32075,"property_crime_count":560,"property_percentile":0.45615067686874633,"property_rate_per_1000":17.45908028059236,"property_score_0_100":45.6,"property_score_label":"average","public_order_crime_count":119,"public_order_percentile":0.5403178340200118,"public_order_rate_per_1000":3.7100545596258767,"public_order_score_0_100":54.0,"public_order_score_label":"average","score_notes":null,"source_count":1,"source_names":"lasd_2024","spatial_incident_count":1509,"total_crime_count":1564,"total_crime_percentile":0.568569746909947,"total_crime_score_0_100":56.9,"total_crime_score_label":"average","total_rate_per_1000":48.76071706936867,"unknown_crime_count":155,"violent_crime_count":247,"violent_percentile":0.5650382577987051,"violent_rate_per_1000":7.70070148090413,"violent_score_0_100":56.5,"violent_score_label":"average","weapons_crime_count":31,"weapons_percentile":0.7433784579164214,"weapons_rate_per_1000":0.9664848012470771,"weapons_score_0_100":74.3,"weapons_score_label":"high","year":2024,"zcta":"90260","zip":"90260"}